audiconnectpy/__init__.py
audiconnectpy/api.py
audiconnectpy/auth.py
audiconnectpy/const.py
audiconnectpy/exceptions.py
audiconnectpy/helpers.py
audiconnectpy/model.py
audiconnectpy/py.typed
audiconnectpy/vehicle.py
audiconnectpy-2.5.50.dist-info/LICENSE
audiconnectpy-2.5.50.dist-info/METADATA
audiconnectpy-2.5.50.dist-info/WHEEL
audiconnectpy-2.5.50.dist-info/top_level.txt
audiconnectpy-2.5.50.dist-info/RECORD
