Metadata-Version: 2.1
Name: audiconnectpy
Version: 2.5.50
Summary: Provides asynchronous authentication and access to Audi Connect
Author-email: Cyr-ius <cyr-ius@ipocus.net>
License: GPL-3
Project-URL: Homepage, https://github.com/cyr-ius/audiconnectpy
Keywords: connect,async,audi
Platform: any
Classifier: Programming Language :: Python
Classifier: Development Status :: 5 - Production/Stable
Classifier: License :: OSI Approved :: GNU General Public License v3 or later (GPLv3+)
Classifier: Programming Language :: Python :: 3
Classifier: Programming Language :: Python :: 3.10
Classifier: Programming Language :: Python :: 3.11
Classifier: Programming Language :: Python :: 3.12
Classifier: Framework :: AsyncIO
Classifier: Intended Audience :: Developers
Classifier: Intended Audience :: System Administrators
Classifier: Topic :: Software Development :: Libraries :: Python Modules
Requires-Python: >=3.10.0
License-File: LICENSE
Requires-Dist: aiohttp>=3.8.1
Requires-Dist: beautifulsoup4>=4.11.2
Requires-Dist: pydantic>=2.8.2
Requires-Dist: pydantic_extra_types>=2.9.0
